zhlite/__init__.py
zhlite/zhlite.py
zhlite-1.8.3.dist-info/LICENSE
zhlite-1.8.3.dist-info/METADATA
zhlite-1.8.3.dist-info/WHEEL
zhlite-1.8.3.dist-info/top_level.txt
zhlite-1.8.3.dist-info/RECORD
